pack_the_folder/__init__.py
pack_the_folder/packer.py
pack_the_folder-0.1.1.dist-info/LICENSE
pack_the_folder-0.1.1.dist-info/METADATA
pack_the_folder-0.1.1.dist-info/WHEEL
pack_the_folder-0.1.1.dist-info/top_level.txt
pack_the_folder-0.1.1.dist-info/RECORD
