Metadata-Version: 2.1
Name: pack_the_folder
Version: 0.1.1
Summary: A simple Python library to pack the contents of a folder into a single file
Home-page: https://github.com/ltoscano/pack_the_folder
Author: Lorenzo Toscano
Author-email: lorenzo.toscano@gmail.com
Classifier: Intended Audience :: Developers
Classifier: License :: OSI Approved :: MIT License
Classifier: Operating System :: OS Independent
Classifier: Programming Language :: Python :: 3
Classifier: Programming Language :: Python :: 3.6
Classifier: Programming Language :: Python :: 3.7
Classifier: Programming Language :: Python :: 3.8
Classifier: Programming Language :: Python :: 3.9
Requires-Python: >=3.6
License-File: LICENSE
